bytemate_patch-0.1.0.dist-info/METADATA
bytemate_patch-0.1.0.dist-info/WHEEL
bytemate_patch-0.1.0.dist-info/licenses/LICENSE
bytemate_patch/__init__.py
bytemate_patch/bytemate_patch.cpython-313-darwin.so
bytemate_patch-0.1.0.dist-info/RECORD
