Metadata-Version: 2.4
Name: bytemate-patch
Version: 0.1.0
Classifier: Programming Language :: Rust
Classifier: Programming Language :: Python :: Implementation :: CPython
Classifier: Programming Language :: Python :: Implementation :: PyPy
License-File: LICENSE
Summary: High-performance JSON patch library
Author-email: Your Name <your.email@example.com>
Requires-Python: >=3.8
